mcp_architecture_gliner/__init__.py
mcp_architecture_gliner/server.py
mcp_architecture_gliner/architecture_gliner/__init__.py
mcp_architecture_gliner/architecture_gliner/mcp_tool.py
mcp_architecture_gliner/architecture_gliner/tool.py
mcp_architecture_gliner/architecture_gliner/config/architecture_labels.yaml
mcp_architecture_gliner/architecture_gliner/models/__init__.py
mcp_architecture_gliner/architecture_gliner/models/architecture_extractor.py
mcp_architecture_gliner-1.0.0.dist-info/METADATA
mcp_architecture_gliner-1.0.0.dist-info/WHEEL
mcp_architecture_gliner-1.0.0.dist-info/entry_points.txt
mcp_architecture_gliner-1.0.0.dist-info/licenses/LICENSE
mcp_architecture_gliner-1.0.0.dist-info/RECORD
