Metadata-Version: 2.4
Name: mcp-architecture-gliner
Version: 1.0.0
Summary: MCP server for architecture-specific entity extraction using GLiNER with TOGAF ADM phase awareness
Project-URL: Homepage, https://github.com/yourusername/mcp-architecture-gliner
Project-URL: Repository, https://github.com/yourusername/mcp-architecture-gliner
Project-URL: Documentation, https://github.com/yourusername/mcp-architecture-gliner#readme
Project-URL: Issues, https://github.com/yourusername/mcp-architecture-gliner/issues
Project-URL: Changelog, https://github.com/yourusername/mcp-architecture-gliner/blob/main/CHANGELOG.md
Author-email: Architecture Team <architecture@example.com>
Maintainer-email: Architecture Team <architecture@example.com>
License: MIT
License-File: LICENSE
Keywords: architecture,entity-extraction,fastmcp,gliner,mcp,model-context-protocol,named-entity-recognition,togaf
Classifier: Development Status :: 4 - Beta
Classifier: Environment :: Console
Classifier: Intended Audience :: Developers
Classifier: Intended Audience :: Information Technology
Classifier: License :: OSI Approved :: MIT License
Classifier: Operating System :: OS Independent
Classifier: Programming Language :: Python :: 3
Classifier: Programming Language :: Python :: 3.9
Classifier: Programming Language :: Python :: 3.10
Classifier: Programming Language :: Python :: 3.11
Classifier: Programming Language :: Python :: 3.12
Classifier: Topic :: Scientific/Engineering :: Artificial Intelligence
Classifier: Topic :: Software Development :: Libraries :: Python Modules
Classifier: Topic :: System :: Distributed Computing
Requires-Python: >=3.9
Requires-Dist: fastmcp>=2.10.0
Requires-Dist: gliner>=0.0.18
Requires-Dist: pydantic>=2.0.0
Requires-Dist: pyyaml>=6.0.0
Requires-Dist: torch>=2.0.0
Provides-Extra: dev
Requires-Dist: black>=23.0.0; extra == 'dev'
Requires-Dist: build>=1.0.0; extra == 'dev'
Requires-Dist: mypy>=1.0.0; extra == 'dev'
Requires-Dist: pre-commit>=3.0.0; extra == 'dev'
Requires-Dist: pytest-asyncio>=0.21.0; extra == 'dev'
Requires-Dist: pytest>=7.0.0; extra == 'dev'
Requires-Dist: ruff>=0.1.0; extra == 'dev'
Requires-Dist: twine>=4.0.0; extra == 'dev'
